rcghci/__init__.py
rcghci/__main__.py
rcghci/rcghci.py
rcghci/rcghci_nvim.py
rcghci-2.1.1.dist-info/METADATA
rcghci-2.1.1.dist-info/RECORD
rcghci-2.1.1.dist-info/WHEEL
rcghci-2.1.1.dist-info/entry_points.txt
rcghci-2.1.1.dist-info/top_level.txt
